MANIFEST.in
setup.py
test.py
Pilot_Lib.egg-info/PKG-INFO
Pilot_Lib.egg-info/SOURCES.txt
Pilot_Lib.egg-info/dependency_links.txt
Pilot_Lib.egg-info/not-zip-safe
Pilot_Lib.egg-info/pbr.json
Pilot_Lib.egg-info/requires.txt
Pilot_Lib.egg-info/top_level.txt
pilot_lib/__init__.py
pilot_lib/__init__.pyc
pilot_lib/config.py
pilot_lib/model.py
pilot_lib/model.pyc
pilot_lib/utils.py
pilot_lib/utils.pyc
pilot_lib/views.py
pilot_lib/views.pyc
pilot_lib/static/pilot/css/bootstrap-social-btns.css
pilot_lib/static/pilot/css/pilotlib_style.css
pilot_lib/static/pilot/js/hello.js
pilot_lib/static/pilot/js/pilot.js
pilot_lib/static/pilot/js/s3upload.js
pilot_lib/templates/PilotTemplates/header-include.html
pilot_lib/templates/PilotTemplates/layout.html
pilot_lib/templates/PilotTemplates/Contact/index.html
pilot_lib/templates/PilotTemplates/Error/index.html
pilot_lib/templates/PilotTemplates/Login/account_settings.html
pilot_lib/templates/PilotTemplates/Login/login-layout.html
pilot_lib/templates/PilotTemplates/Login/login.html
pilot_lib/templates/PilotTemplates/Login/lost_password.html
pilot_lib/templates/PilotTemplates/Login/set_email.html
pilot_lib/templates/PilotTemplates/Login/signup.html
pilot_lib/templates/PilotTemplates/Maintenance/index.html
pilot_lib/templates/PilotTemplates/UserAdmin/get.html
pilot_lib/templates/PilotTemplates/UserAdmin/index.html
pilot_lib/templates/PilotTemplates/macros/base.html
pilot_lib/templates/PilotTemplates/macros/forms.html