Metadata-Version: 1.1
Name: Pilot-Lib
Version: 0.0.17
Summary: Pilot-Lib
Home-page: https://github.com/mardix/flask-pilot
Author: Mardix
Author-email: mardix@github.com
License: MIT
Download-URL: http://github.com/mardix/flask-pilot/tarball/master
Keywords: pilot
Platform: any
Classifier: Environment :: Web Environment
Classifier: Intended Audience :: Developers
Classifier: License :: OSI Approved :: BSD License
Classifier: Operating System :: OS Independent
Classifier: Programming Language :: Python
Classifier: Programming Language :: Python :: 2
Classifier: Programming Language :: Python :: 2.6
Classifier: Programming Language :: Python :: 2.7
Classifier: Programming Language :: Python :: 3
Classifier: Programming Language :: Python :: 3.3
Classifier: Programming Language :: Python :: 3.4
Classifier: Topic :: Internet :: WWW/HTTP :: Dynamic Content
Classifier: Topic :: Software Development :: Libraries :: Python Modules
